{"dexterity": 13, "intelligence": 1, "actions": [{"damage_dice": "4d4", "attack_bonus": 3, "name": "Bites", "desc": "Melee Weapon Attack: +3 to hit, reach 0 ft., one target in the swarm's space. Hit: 10 (4d4) piercing damage, or 5 (2d4) piercing damage if the swarm has half of its hit points or fewer."}], "hit_dice": "5d8", "damage_resistances": "bludgeoning, piercing, slashing", "speed": "5 ft., fly 30 ft.", "alignment": "unaligned", "size": "Medium", "index": 281, "strength": 3, "constitution": 10, "languages": "", "charisma": 1, "armor_class": 12, "condition_immunities": "charmed, frightened, grappled, paralyzed, petrified, prone, restrained, stunned", "damage_vulnerabilities": "", "senses": "blindsight 10 ft., passive Perception 8", "wisdom": 7, "challenge_rating": 0.5, "special_abilities": [{"attack_bonus": 0, "name": "Swarm", "desc": "The swarm can occupy another creature's space and vice versa, and the swarm can move through any opening large enough for a Tiny insect. The swarm can't regain hit points or gain temporary hit points."}], "name": "Swarm of Wasps", "url": "http://www.dnd5eapi.co/api/monsters/281", "type": "swarm of Tiny beasts", "damage_immunities": "", "subtype": "", "hit_points": 22, "_id": "592f6c32c9e7ce9f721580e2"}